Metadata-Version: 2.4
Name: pygremlinbox-cc-by-nc-nd-3-0-igo
Version: 1.4.0
Summary: PyGremlinBox CC-BY-NC-ND-3.0-IGO - Supply chain security testing module with CC-BY-NC-ND-3.0-IGO licence
Author-email: Supply Chain Security Tester <simon@sigre.xyz>
Maintainer-email: Supply Chain Security Tester <simon@sigre.xyz>
License: CC-BY-NC-ND-3.0-IGO
Project-URL: Homepage, https://github.com/gocortexio/pygremlinbox
Project-URL: Repository, https://github.com/gocortexio/pygremlinbox.git
Project-URL: Issues, https://github.com/gocortexio/pygremlinbox/issues
Keywords: security,supply-chain,testing,licence
Classifier: Development Status :: 4 - Beta
Classifier: Intended Audience :: Developers
Classifier: Operating System :: OS Independent
Classifier: Programming Language :: Python :: 3
Classifier: Programming Language :: Python :: 3.8
Classifier: Programming Language :: Python :: 3.9
Classifier: Programming Language :: Python :: 3.10
Classifier: Programming Language :: Python :: 3.11
Classifier: Programming Language :: Python :: 3.12
Classifier: Topic :: Security
Classifier: Topic :: Software Development :: Testing
Requires-Python: >=3.8
License-File: LICENCE
Dynamic: license-file
